Metadata-Version: 2.1
Name: odoo14-addon-assets_management
Version: 14.0.1.7.0
Summary: Gestione Cespiti
Home-page: https://github.com/OCA/l10n-italy
Author: Openforce, Odoo Community Association (OCA)
Author-email: support@odoo-community.org
License: AGPL-3
Classifier: Programming Language :: Python
Classifier: Framework :: Odoo
Classifier: Framework :: Odoo :: 14.0
Classifier: License :: OSI Approved :: GNU Affero General Public License v3
Classifier: Development Status :: 4 - Beta
Requires-Python: >=3.6
Requires-Dist: odoo14-addon-account-financial-report
Requires-Dist: odoo14-addon-account-fiscal-year
Requires-Dist: odoo<14.1dev,>=14.0a
